[
  {
    "FIO": "Степашин Николай Николаевич",
    "DPZ": "2019-09-12T01:42:36",
    "Napravlenie": "Бюджетная основа",
    "Osnovanie": "Биофизика",
    "IDs": []
  },
  {
    "FIO": "Синичкин Иван Иванович",
    "DPZ": "2019-09-12T09:59:09",
    "Napravlenie": "Бюджетная основа",
    "Osnovanie": "Археология",
    "IDs": [
      { "ID": "Спортивные достижения", "Ocenka": 5 },
      { "ID": "Сочинение", "Ocenka": 1 },
      { "ID": "Волонтерская деятельность", "Ocenka": 3 }
    ]
  },
  {
    "FIO": "Кедрова Анна Николаевна",
    "DPZ": "2019-09-12T01:19:57",
    "Napravlenie": "Бюджетная основа",
    "Osnovanie": "Археология",
    "IDs": [
      { "ID": "Спортивные достижения", "Ocenka": 5 },
      { "ID": "Сочинение", "Ocenka": 1 },
      { "ID": "Волонтерская деятельность", "Ocenka": 3 }
    ]
  },
  {
    "FIO": "Синичкин Иван Иванович",
    "DPZ": "2019-09-12T09:59:09",
    "Napravlenie": "Полное возмещение затрат",
    "Osnovanie": "Археология",
    "IDs": [
      { "ID": "Спортивные достижения", "Ocenka": 5 },
      { "ID": "Сочинение", "Ocenka": 1 }
    ]
  },
  {
    "FIO": "Катков Сидор Петрович",
    "DPZ": "2019-09-12T01:58:23",
    "Napravlenie": "Полное возмещение затрат",
    "Osnovanie": "Археология",
    "IDs": [
      { "ID": "Спортивные достижения", "Ocenka": 5 },
      { "ID": "Сочинение", "Ocenka": 1 }
    ]
  },
  {
    "FIO": "Сомов Алексей Алексеевич",
    "DPZ": "2019-09-12T02:03:37",
    "Napravlenie": "Целевой прием",
    "Osnovanie": "Археология",
    "IDs": []
  }
]
